skanetrafiken.py
skanetrafiken-2.2.0.dist-info/METADATA
skanetrafiken-2.2.0.dist-info/WHEEL
skanetrafiken-2.2.0.dist-info/top_level.txt
skanetrafiken-2.2.0.dist-info/RECORD
