Metadata-Version: 2.1
Name: skanetrafiken
Version: 2.2.0
Summary: Python wrapper for Skanetrafiken Open API
Home-page: https://github.com/peterstark72/skanetrafiken
Author: Peter Stark
Author-email: peterstark72@gmail.com
License: UNKNOWN
Platform: UNKNOWN
Classifier: Development Status :: 4 - Beta
Classifier: Intended Audience :: Developers
Classifier: License :: Free for non-commercial use
Classifier: Natural Language :: Swedish
Classifier: Programming Language :: Python :: 3.5
Classifier: Topic :: Internet
Requires-Dist: lxml
